qiniu_lite/__init__.py
qiniu_lite/core.py
qiniu_lite-1.0.1.dist-info/DESCRIPTION.rst
qiniu_lite-1.0.1.dist-info/METADATA
qiniu_lite-1.0.1.dist-info/RECORD
qiniu_lite-1.0.1.dist-info/WHEEL
qiniu_lite-1.0.1.dist-info/metadata.json
qiniu_lite-1.0.1.dist-info/top_level.txt
